hermit/__init__.py
hermit/__main__.py
memhermit-0.0.1.dist-info/METADATA
memhermit-0.0.1.dist-info/WHEEL
memhermit-0.0.1.dist-info/top_level.txt
memhermit-0.0.1.dist-info/RECORD
